metaflow_diff/__init__.py
metaflow_diff/metaflow_diff.py
metaflow_diff-0.1.7.dist-info/LICENSE
metaflow_diff-0.1.7.dist-info/METADATA
metaflow_diff-0.1.7.dist-info/WHEEL
metaflow_diff-0.1.7.dist-info/entry_points.txt
metaflow_diff-0.1.7.dist-info/top_level.txt
metaflow_diff-0.1.7.dist-info/RECORD
